<?xml version="1.0" standalone="yes"?>
<mpnFieldOpDataSet>
  <xs:schema id="mpnFieldOpDataSet" xmlns="" xmlns:xs="http://www.w3.org/2001/XMLSchema" xmlns:msdata="urn:schemas-microsoft-com:xml-msdata">
    <xs:element name="mpnFieldOpDataSet" msdata:IsDataSet="true" msdata:UseCurrentLocale="true" msdata:CacheSize="500">
      <xs:complexType>
        <xs:choice minOccurs="0" maxOccurs="unbounded">
          <xs:element name="FieldOp">
            <xs:complexType>
              <xs:sequence>
                <xs:element name="FieldOpKey" msdata:DataType="System.Guid, mscorlib, Version=2.0.0.0, Culture=neutral, PublicKeyToken=b77a5c561934e089" type="xs:string" />
                <xs:element name="TaskRef" type="xs:string" default="" minOccurs="0" />
                <xs:element name="Name" type="xs:string" default="" minOccurs="0" />
                <xs:element name="ParentFieldOpKey" msdata:DataType="System.Guid, mscorlib, Version=2.0.0.0, Culture=neutral, PublicKeyToken=b77a5c561934e089" type="xs:string" minOccurs="0" />
                <xs:element name="IsPlanned" type="xs:boolean" default="false" minOccurs="0" />
                <xs:element name="SrcFieldOpKey" msdata:DataType="System.Guid, mscorlib, Version=2.0.0.0, Culture=neutral, PublicKeyToken=b77a5c561934e089" type="xs:string" minOccurs="0" />
                <xs:element name="DstFieldOpKey" msdata:DataType="System.Guid, mscorlib, Version=2.0.0.0, Culture=neutral, PublicKeyToken=b77a5c561934e089" type="xs:string" minOccurs="0" />
                <xs:element name="Version" type="xs:string" default="7.0.1006" minOccurs="0" />
                <xs:element name="HostRef" type="xs:string" default="" minOccurs="0" />
                <xs:element name="IsObservation" type="xs:boolean" default="false" minOccurs="0" />
                <xs:element name="DomainRef" type="xs:string" default="" minOccurs="0" />
                <xs:element name="ScheduleMethod" type="xs:int" default="0" minOccurs="0" />
                <xs:element name="ScheduledGDUs" type="xs:int" default="0" minOccurs="0" />
                <xs:element name="ScheduledDays" type="xs:int" default="0" minOccurs="0" />
                <xs:element name="ScheduledDate" type="xs:dateTime" minOccurs="0" />
                <xs:element name="ScheduledGrowthStageRef" type="xs:string" default="" minOccurs="0" />
                <xs:element name="ScheduledTaskRef" type="xs:string" default="" minOccurs="0" />
                <xs:element name="SourceName" type="xs:string" default="" minOccurs="0" />
              </xs:sequence>
            </xs:complexType>
          </xs:element>
          <xs:element name="OpRegion">
            <xs:complexType>
              <xs:sequence>
                <xs:element name="FieldOpKey" msdata:DataType="System.Guid, mscorlib, Version=2.0.0.0, Culture=neutral, PublicKeyToken=b77a5c561934e089" type="xs:string" minOccurs="0" />
                <xs:element name="OpRegionKey" msdata:DataType="System.Guid, mscorlib, Version=2.0.0.0, Culture=neutral, PublicKeyToken=b77a5c561934e089" type="xs:string" />
                <xs:element name="Name" type="xs:string" default="" minOccurs="0" />
                <xs:element name="StartTime" type="xs:dateTime" minOccurs="0" />
                <xs:element name="EndTime" type="xs:dateTime" minOccurs="0" />
                <xs:element name="Area" type="xs:double" default="0" minOccurs="0" />
                <xs:element name="AreaUnit" type="xs:int" default="0" minOccurs="0" />
                <xs:element name="DateCreated" type="xs:dateTime" minOccurs="0" />
                <xs:element name="DatePosted" type="xs:dateTime" minOccurs="0" />
                <xs:element name="ParentOpRegionKey" msdata:DataType="System.Guid, mscorlib, Version=2.0.0.0, Culture=neutral, PublicKeyToken=b77a5c561934e089" type="xs:string" minOccurs="0" />
                <xs:element name="BoundaryXML" type="xs:string" default="" minOccurs="0" />
                <xs:element name="CropRef" type="xs:string" default="" minOccurs="0" />
                <xs:element name="Notes" type="xs:string" default="" minOccurs="0" />
                <xs:element name="Version" type="xs:string" default="7.0.1006" minOccurs="0" />
                <xs:element name="LegacyOpRegion" type="xs:string" default="" minOccurs="0" />
                <xs:element name="HostRef" type="xs:string" default="" minOccurs="0" />
                <xs:element name="SourceName" type="xs:string" default="" minOccurs="0" />
                <xs:element name="ArchiveSetRef" type="xs:string" minOccurs="0" />
                <xs:element name="MonitorBrand" type="xs:string" minOccurs="0" />
                <xs:element name="MonitorModel" type="xs:string" minOccurs="0" />
                <xs:element name="MonitorVersion" type="xs:string" minOccurs="0" />
                <xs:element name="CardManagerRef" type="xs:string" minOccurs="0" />
              </xs:sequence>
            </xs:complexType>
          </xs:element>
          <xs:element name="TaskPropertyUse">
            <xs:complexType>
              <xs:sequence>
                <xs:element name="OpRegionKey" msdata:DataType="System.Guid, mscorlib, Version=2.0.0.0, Culture=neutral, PublicKeyToken=b77a5c561934e089" type="xs:string" minOccurs="0" />
                <xs:element name="TaskPropertyUseKey" msdata:DataType="System.Guid, mscorlib, Version=2.0.0.0, Culture=neutral, PublicKeyToken=b77a5c561934e089" type="xs:string" />
                <xs:element name="TaskPropertyRef" type="xs:string" default="" minOccurs="0" />
                <xs:element name="Name" type="xs:string" default="" minOccurs="0" />
                <xs:element name="Value" type="xs:string" default="" minOccurs="0" />
                <xs:element name="Version" type="xs:string" default="7.0.1006" minOccurs="0" />
                <xs:element name="SourceName" type="xs:string" default="" minOccurs="0" />
                <xs:element name="PropertyType" type="xs:int" default="0" minOccurs="0" />
              </xs:sequence>
            </xs:complexType>
          </xs:element>
          <xs:element name="MachineUse">
            <xs:complexType>
              <xs:sequence>
                <xs:element name="OpRegionKey" msdata:DataType="System.Guid, mscorlib, Version=2.0.0.0, Culture=neutral, PublicKeyToken=b77a5c561934e089" type="xs:string" minOccurs="0" />
                <xs:element name="MachineUseKey" msdata:DataType="System.Guid, mscorlib, Version=2.0.0.0, Culture=neutral, PublicKeyToken=b77a5c561934e089" type="xs:string" />
                <xs:element name="MachineRef" type="xs:string" default="" minOccurs="0" />
                <xs:element name="Name" type="xs:string" default="" minOccurs="0" />
                <xs:element name="Version" type="xs:string" default="7.0.1006" minOccurs="0" />
                <xs:element name="HostRef" type="xs:string" default="" minOccurs="0" />
                <xs:element name="SourceName" type="xs:string" default="" minOccurs="0" />
              </xs:sequence>
            </xs:complexType>
          </xs:element>
          <xs:element name="OperatorUse">
            <xs:complexType>
              <xs:sequence>
                <xs:element name="OpRegionKey" msdata:DataType="System.Guid, mscorlib, Version=2.0.0.0, Culture=neutral, PublicKeyToken=b77a5c561934e089" type="xs:string" minOccurs="0" />
                <xs:element name="OperatorUseKey" msdata:DataType="System.Guid, mscorlib, Version=2.0.0.0, Culture=neutral, PublicKeyToken=b77a5c561934e089" type="xs:string" />
                <xs:element name="OperatorRef" type="xs:string" default="" minOccurs="0" />
                <xs:element name="Name" type="xs:string" default="" minOccurs="0" />
                <xs:element name="Version" type="xs:string" default="7.0.1006" minOccurs="0" />
                <xs:element name="HostRef" type="xs:string" default="" minOccurs="0" />
                <xs:element name="SourceName" type="xs:string" default="" minOccurs="0" />
              </xs:sequence>
            </xs:complexType>
          </xs:element>
          <xs:element name="ContainerUse">
            <xs:complexType>
              <xs:sequence>
                <xs:element name="OpRegionKey" msdata:DataType="System.Guid, mscorlib, Version=2.0.0.0, Culture=neutral, PublicKeyToken=b77a5c561934e089" type="xs:string" minOccurs="0" />
                <xs:element name="ContainerUseKey" msdata:DataType="System.Guid, mscorlib, Version=2.0.0.0, Culture=neutral, PublicKeyToken=b77a5c561934e089" type="xs:string" />
                <xs:element name="ContainerRef" type="xs:string" default="" minOccurs="0" />
                <xs:element name="Name" type="xs:string" default="" minOccurs="0" />
                <xs:element name="SourceName" type="xs:string" default="" minOccurs="0" />
                <xs:element name="ParentContainerUseKey" msdata:DataType="System.Guid, mscorlib, Version=2.0.0.0, Culture=neutral, PublicKeyToken=b77a5c561934e089" type="xs:string" minOccurs="0" />
                <xs:element name="Version" type="xs:string" default="7.0.1006" minOccurs="0" />
              </xs:sequence>
            </xs:complexType>
          </xs:element>
          <xs:element name="ProductUse">
            <xs:complexType>
              <xs:sequence>
                <xs:element name="OpRegionKey" msdata:DataType="System.Guid, mscorlib, Version=2.0.0.0, Culture=neutral, PublicKeyToken=b77a5c561934e089" type="xs:string" minOccurs="0" />
                <xs:element name="ProductUseKey" msdata:DataType="System.Guid, mscorlib, Version=2.0.0.0, Culture=neutral, PublicKeyToken=b77a5c561934e089" type="xs:string" />
                <xs:element name="ProductLotRef" type="xs:string" default="" minOccurs="0" />
                <xs:element name="Name" type="xs:string" default="" minOccurs="0" />
                <xs:element name="Rate" type="xs:double" default="0" minOccurs="0" />
                <xs:element name="RateUnit" type="xs:int" default="0" minOccurs="0" />
                <xs:element name="Quantity" type="xs:double" default="0" minOccurs="0" />
                <xs:element name="QuantityUnit" type="xs:int" default="0" minOccurs="0" />
                <xs:element name="PercentCoverage" type="xs:double" default="100" minOccurs="0" />
                <xs:element name="ParentProductUseKey" msdata:DataType="System.Guid, mscorlib, Version=2.0.0.0, Culture=neutral, PublicKeyToken=b77a5c561934e089" type="xs:string" minOccurs="0" />
                <xs:element name="Area" type="xs:double" default="0" minOccurs="0" />
                <xs:element name="AreaUnit" type="xs:int" default="0" minOccurs="0" />
                <xs:element name="SourceName" type="xs:string" default="" minOccurs="0" />
                <xs:element name="Version" type="xs:string" default="7.0.1006" minOccurs="0" />
                <xs:element name="HostRef" type="xs:string" default="" minOccurs="0" />
                <xs:element name="ProductType" type="xs:int" default="0" minOccurs="0" />
                <xs:element name="ProductForm" type="xs:int" default="0" minOccurs="0" />
                <xs:element name="MixConcentration" type="xs:double" default="0" minOccurs="0" />
                <xs:element name="MixConcentrationUnit" type="xs:int" default="0" minOccurs="0" />
                <xs:element name="BoundaryXML" type="xs:string" default="" minOccurs="0" />
                <xs:element name="SourceRate" type="xs:double" default="0" minOccurs="0" />
                <xs:element name="SourceQuantity" type="xs:double" default="0" minOccurs="0" />
                <xs:element name="SourceArea" type="xs:double" default="0" minOccurs="0" />
                <xs:element name="IsRateDocumented" type="xs:boolean" default="false" />
                <xs:element name="IsQuantityDocumented" type="xs:boolean" default="false" />
                <xs:element name="IsAreaDocumented" type="xs:boolean" default="false" />
                <xs:element name="AmendmentRef" type="xs:string" default="" minOccurs="0" />
                <xs:element name="AmendmentFactor" type="xs:double" default="0" minOccurs="0" />
                <xs:element name="AmendmentUnit" type="xs:int" default="0" minOccurs="0" />
                <xs:element name="Treatment" default="" minOccurs="0">
                  <xs:simpleType>
                    <xs:restriction base="xs:string">
                      <xs:maxLength value="32" />
                    </xs:restriction>
                  </xs:simpleType>
                </xs:element>
              </xs:sequence>
            </xs:complexType>
          </xs:element>
          <xs:element name="ContainerProductUse">
            <xs:complexType>
              <xs:sequence>
                <xs:element name="ContainerProductUseKey" msdata:DataType="System.Guid, mscorlib, Version=2.0.0.0, Culture=neutral, PublicKeyToken=b77a5c561934e089" type="xs:string" />
                <xs:element name="ContainerUseKey" msdata:DataType="System.Guid, mscorlib, Version=2.0.0.0, Culture=neutral, PublicKeyToken=b77a5c561934e089" type="xs:string" minOccurs="0" />
                <xs:element name="ProductUseKey" msdata:DataType="System.Guid, mscorlib, Version=2.0.0.0, Culture=neutral, PublicKeyToken=b77a5c561934e089" type="xs:string" minOccurs="0" />
                <xs:element name="Version" type="xs:string" default="7.0.1006" minOccurs="0" />
              </xs:sequence>
            </xs:complexType>
          </xs:element>
          <xs:element name="ComponentUse">
            <xs:complexType>
              <xs:sequence>
                <xs:element name="OpRegionKey" msdata:DataType="System.Guid, mscorlib, Version=2.0.0.0, Culture=neutral, PublicKeyToken=b77a5c561934e089" type="xs:string" minOccurs="0" />
                <xs:element name="ComponentUseKey" msdata:DataType="System.Guid, mscorlib, Version=2.0.0.0, Culture=neutral, PublicKeyToken=b77a5c561934e089" type="xs:string" />
                <xs:element name="ComponentRef" type="xs:string" default="" minOccurs="0" />
                <xs:element name="Name" type="xs:string" default="" minOccurs="0" />
                <xs:element name="WidthMode" type="xs:int" default="0" minOccurs="0" />
                <xs:element name="FCDComponentWidthIndex" type="xs:int" default="0" minOccurs="0" />
                <xs:element name="Width" type="xs:double" default="0" minOccurs="0" />
                <xs:element name="EngagedMode" type="xs:int" default="0" minOccurs="0" />
                <xs:element name="FCDComponentEngagedIndex" type="xs:int" default="0" minOccurs="0" />
                <xs:element name="OffsetUnit" type="xs:int" default="0" minOccurs="0" />
                <xs:element name="OffsetInline" type="xs:double" default="0" minOccurs="0" />
                <xs:element name="OffsetLateral" type="xs:double" default="0" minOccurs="0" />
                <xs:element name="OffsetVertical" type="xs:double" default="0" minOccurs="0" />
                <xs:element name="PostCalM" type="xs:double" default="0" minOccurs="0" />
                <xs:element name="PostCalB" type="xs:double" default="0" minOccurs="0" />
                <xs:element name="SourceName" type="xs:string" default="" minOccurs="0" />
                <xs:element name="ParentComponentUseKey" msdata:DataType="System.Guid, mscorlib, Version=2.0.0.0, Culture=neutral, PublicKeyToken=b77a5c561934e089" type="xs:string" minOccurs="0" />
                <xs:element name="Version" type="xs:string" default="7.0.1006" minOccurs="0" />
              </xs:sequence>
            </xs:complexType>
          </xs:element>
          <xs:element name="SensorUse">
            <xs:complexType>
              <xs:sequence>
                <xs:element name="OpRegionKey" msdata:DataType="System.Guid, mscorlib, Version=2.0.0.0, Culture=neutral, PublicKeyToken=b77a5c561934e089" type="xs:string" minOccurs="0" />
                <xs:element name="SensorUseKey" msdata:DataType="System.Guid, mscorlib, Version=2.0.0.0, Culture=neutral, PublicKeyToken=b77a5c561934e089" type="xs:string" />
                <xs:element name="SensorRef" type="xs:string" default="" minOccurs="0" />
                <xs:element name="Name" type="xs:string" default="" minOccurs="0" />
                <xs:element name="Classification" type="xs:string" default="" minOccurs="0" />
                <xs:element name="ComponentUseKey" msdata:DataType="System.Guid, mscorlib, Version=2.0.0.0, Culture=neutral, PublicKeyToken=b77a5c561934e089" type="xs:string" minOccurs="0" />
                <xs:element name="ContainerUseKey" msdata:DataType="System.Guid, mscorlib, Version=2.0.0.0, Culture=neutral, PublicKeyToken=b77a5c561934e089" type="xs:string" minOccurs="0" />
                <xs:element name="MasterUseKey" msdata:DataType="System.Guid, mscorlib, Version=2.0.0.0, Culture=neutral, PublicKeyToken=b77a5c561934e089" type="xs:string" minOccurs="0" />
                <xs:element name="AdjustmentUseKey" msdata:DataType="System.Guid, mscorlib, Version=2.0.0.0, Culture=neutral, PublicKeyToken=b77a5c561934e089" type="xs:string" minOccurs="0" />
                <xs:element name="SourceName" type="xs:string" default="" minOccurs="0" />
                <xs:element name="Version" type="xs:string" default="7.0.1006" minOccurs="0" />
              </xs:sequence>
            </xs:complexType>
          </xs:element>
          <xs:element name="SensorValue">
            <xs:complexType>
              <xs:sequence>
                <xs:element name="SensorUseKey" msdata:DataType="System.Guid, mscorlib, Version=2.0.0.0, Culture=neutral, PublicKeyToken=b77a5c561934e089" type="xs:string" />
                <xs:element name="SensorValueType" type="xs:int" default="0" />
                <xs:element name="Unit" type="xs:int" default="0" minOccurs="0" />
                <xs:element name="Value" type="xs:double" default="0" minOccurs="0" />
                <xs:element name="FCDIndex" type="xs:int" default="0" minOccurs="0" />
                <xs:element name="Version" type="xs:string" default="7.0.1006" minOccurs="0" />
                <xs:element name="PostCalM" type="xs:double" default="1" minOccurs="0" />
                <xs:element name="PostCalB" type="xs:double" default="0" minOccurs="0" />
                <xs:element name="SourceValue" type="xs:double" default="0" minOccurs="0" />
                <xs:element name="IsValueDocumented" type="xs:boolean" default="false" />
              </xs:sequence>
            </xs:complexType>
          </xs:element>
          <xs:element name="Tags">
            <xs:complexType>
              <xs:sequence>
                <xs:element name="ParentTableID" type="xs:int" default="0" minOccurs="0" />
                <xs:element name="ParentKey" msdata:DataType="System.Guid, mscorlib, Version=2.0.0.0, Culture=neutral, PublicKeyToken=b77a5c561934e089" type="xs:string" />
                <xs:element name="TagID" type="xs:int" default="0" />
                <xs:element name="Value" default="" minOccurs="0">
                  <xs:simpleType>
                    <xs:restriction base="xs:string">
                      <xs:maxLength value="32" />
                    </xs:restriction>
                  </xs:simpleType>
                </xs:element>
                <xs:element name="Version" type="xs:string" default="7.0.1006" minOccurs="0" />
              </xs:sequence>
            </xs:complexType>
          </xs:element>
        </xs:choice>
      </xs:complexType>
      <xs:unique name="FieldOpKey" msdata:PrimaryKey="true">
        <xs:selector xpath=".//FieldOp" />
        <xs:field xpath="FieldOpKey" />
      </xs:unique>
      <xs:unique name="OpRegionKey" msdata:PrimaryKey="true">
        <xs:selector xpath=".//OpRegion" />
        <xs:field xpath="OpRegionKey" />
      </xs:unique>
      <xs:unique name="PropertyUseKey" msdata:PrimaryKey="true">
        <xs:selector xpath=".//TaskPropertyUse" />
        <xs:field xpath="TaskPropertyUseKey" />
      </xs:unique>
      <xs:unique name="Constraint1" msdata:PrimaryKey="true">
        <xs:selector xpath=".//MachineUse" />
        <xs:field xpath="MachineUseKey" />
      </xs:unique>
      <xs:unique name="OperatorUse_Constraint1" msdata:ConstraintName="Constraint1" msdata:PrimaryKey="true">
        <xs:selector xpath=".//OperatorUse" />
        <xs:field xpath="OperatorUseKey" />
      </xs:unique>
      <xs:unique name="ContainerUseKey" msdata:PrimaryKey="true">
        <xs:selector xpath=".//ContainerUse" />
        <xs:field xpath="ContainerUseKey" />
      </xs:unique>
      <xs:unique name="ProductUseKey" msdata:PrimaryKey="true">
        <xs:selector xpath=".//ProductUse" />
        <xs:field xpath="ProductUseKey" />
      </xs:unique>
      <xs:unique name="ContainerProductUse_Constraint1" msdata:ConstraintName="Constraint1" msdata:PrimaryKey="true">
        <xs:selector xpath=".//ContainerProductUse" />
        <xs:field xpath="ContainerProductUseKey" />
      </xs:unique>
      <xs:unique name="ComponentUseKey" msdata:PrimaryKey="true">
        <xs:selector xpath=".//ComponentUse" />
        <xs:field xpath="ComponentUseKey" />
      </xs:unique>
      <xs:unique name="SensorUse_Constraint1" msdata:ConstraintName="Constraint1" msdata:PrimaryKey="true">
        <xs:selector xpath=".//SensorUse" />
        <xs:field xpath="SensorUseKey" />
      </xs:unique>
      <xs:unique name="SensorValueKey1" msdata:PrimaryKey="true">
        <xs:selector xpath=".//SensorValue" />
        <xs:field xpath="SensorUseKey" />
        <xs:field xpath="SensorValueType" />
      </xs:unique>
      <xs:unique name="Tags_Constraint1" msdata:ConstraintName="Constraint1" msdata:PrimaryKey="true">
        <xs:selector xpath=".//Tags" />
        <xs:field xpath="ParentKey" />
        <xs:field xpath="TagID" />
      </xs:unique>
      <xs:keyref name="FK_SensorUse_SensorValue" refer="SensorUse_Constraint1">
        <xs:selector xpath=".//SensorValue" />
        <xs:field xpath="SensorUseKey" />
      </xs:keyref>
      <xs:keyref name="FK_SensorUse_MasterSensorUse" refer="SensorUse_Constraint1" msdata:DeleteRule="SetNull">
        <xs:selector xpath=".//SensorUse" />
        <xs:field xpath="MasterUseKey" />
      </xs:keyref>
      <xs:keyref name="FK_SensorUse_AdjustmentSensorUse" refer="SensorUse_Constraint1" msdata:DeleteRule="SetNull">
        <xs:selector xpath=".//SensorUse" />
        <xs:field xpath="AdjustmentUseKey" />
      </xs:keyref>
      <xs:keyref name="FK_OpRegion_SensorUse" refer="OpRegionKey">
        <xs:selector xpath=".//SensorUse" />
        <xs:field xpath="OpRegionKey" />
      </xs:keyref>
      <xs:keyref name="FK_ComponentUse_SensorUse" refer="ComponentUseKey">
        <xs:selector xpath=".//SensorUse" />
        <xs:field xpath="ComponentUseKey" />
      </xs:keyref>
      <xs:keyref name="FK_ContainerUse_SensorUse" refer="ContainerUseKey">
        <xs:selector xpath=".//SensorUse" />
        <xs:field xpath="ContainerUseKey" />
      </xs:keyref>
      <xs:keyref name="FK_ComponentUse_ParentComponentUse" refer="ComponentUseKey" msdata:DeleteRule="SetNull">
        <xs:selector xpath=".//ComponentUse" />
        <xs:field xpath="ParentComponentUseKey" />
      </xs:keyref>
      <xs:keyref name="FK_OpRegion_ComponentUse" refer="OpRegionKey">
        <xs:selector xpath=".//ComponentUse" />
        <xs:field xpath="OpRegionKey" />
      </xs:keyref>
      <xs:keyref name="FK_ProductUse_ContainerProductUse" refer="ProductUseKey">
        <xs:selector xpath=".//ContainerProductUse" />
        <xs:field xpath="ProductUseKey" />
      </xs:keyref>
      <xs:keyref name="FK_ContainerUse_ContainerProductUse" refer="ContainerUseKey">
        <xs:selector xpath=".//ContainerProductUse" />
        <xs:field xpath="ContainerUseKey" />
      </xs:keyref>
      <xs:keyref name="FK_ProductUse_ParentProductUse" refer="ProductUseKey" msdata:DeleteRule="SetNull">
        <xs:selector xpath=".//ProductUse" />
        <xs:field xpath="ParentProductUseKey" />
      </xs:keyref>
      <xs:keyref name="OpRegion_ProductUse" refer="OpRegionKey">
        <xs:selector xpath=".//ProductUse" />
        <xs:field xpath="OpRegionKey" />
      </xs:keyref>
      <xs:keyref name="FK_ContainerUse_ParentContainerUse" refer="ContainerUseKey" msdata:DeleteRule="SetNull">
        <xs:selector xpath=".//ContainerUse" />
        <xs:field xpath="ParentContainerUseKey" />
      </xs:keyref>
      <xs:keyref name="FK_OpRegion_ContainerUse" refer="OpRegionKey">
        <xs:selector xpath=".//ContainerUse" />
        <xs:field xpath="OpRegionKey" />
      </xs:keyref>
      <xs:keyref name="FK_OpRegion_OperatorUse" refer="OpRegionKey">
        <xs:selector xpath=".//OperatorUse" />
        <xs:field xpath="OpRegionKey" />
      </xs:keyref>
      <xs:keyref name="FK_OpRegion_MachineUse" refer="OpRegionKey">
        <xs:selector xpath=".//MachineUse" />
        <xs:field xpath="OpRegionKey" />
      </xs:keyref>
      <xs:keyref name="FK_OpRegion_PropertyUse" refer="OpRegionKey">
        <xs:selector xpath=".//TaskPropertyUse" />
        <xs:field xpath="OpRegionKey" />
      </xs:keyref>
      <xs:keyref name="FK_OpRegion_ParentOpRegion" refer="OpRegionKey" msdata:DeleteRule="SetNull">
        <xs:selector xpath=".//OpRegion" />
        <xs:field xpath="ParentOpRegionKey" />
      </xs:keyref>
      <xs:keyref name="FK_FieldOp_OpRegion" refer="FieldOpKey">
        <xs:selector xpath=".//OpRegion" />
        <xs:field xpath="FieldOpKey" />
      </xs:keyref>
      <xs:keyref name="FK_FieldOp_DstFieldOp" refer="FieldOpKey" msdata:DeleteRule="SetNull">
        <xs:selector xpath=".//FieldOp" />
        <xs:field xpath="DstFieldOpKey" />
      </xs:keyref>
      <xs:keyref name="FK_FieldOp_SrcFieldOp" refer="FieldOpKey" msdata:DeleteRule="SetNull">
        <xs:selector xpath=".//FieldOp" />
        <xs:field xpath="SrcFieldOpKey" />
      </xs:keyref>
      <xs:keyref name="FK_FieldOp_ParentFieldOp" refer="FieldOpKey" msdata:DeleteRule="SetNull">
        <xs:selector xpath=".//FieldOp" />
        <xs:field xpath="ParentFieldOpKey" />
      </xs:keyref>
    </xs:element>
  </xs:schema>
  <FieldOp>
    <FieldOpKey>60b1a264-edc7-4e0d-95a0-23ae2b3adff0</FieldOpKey>
    <TaskRef>Test</TaskRef>
    <Name />
    <IsPlanned>false</IsPlanned>
    <Version>7.0.1006</Version>
    <HostRef />
    <IsObservation>false</IsObservation>
    <DomainRef />
    <ScheduleMethod>0</ScheduleMethod>
    <ScheduledGDUs>0</ScheduledGDUs>
    <ScheduledDays>0</ScheduledDays>
    <ScheduledGrowthStageRef />
    <ScheduledTaskRef />
    <SourceName />
  </FieldOp>
</mpnFieldOpDataSet>